gst_mcp/__init__.py
gst_mcp/caps.py
gst_mcp/docs.py
gst_mcp/examples.py
gst_mcp/pipeline.py
gst_mcp/py.typed
gst_mcp/registry.py
gst_mcp/server.py
gst_mcp-0.1.0.dist-info/WHEEL
gst_mcp-0.1.0.dist-info/entry_points.txt
gst_mcp-0.1.0.dist-info/METADATA
gst_mcp-0.1.0.dist-info/RECORD
