Metadata-Version: 2.4
Name: gst-mcp
Version: 0.1.0
Summary: MCP server for GStreamer introspection and pipeline development
Keywords: mcp,gstreamer,multimedia,video,audio,pipeline,llm,claude,ai
Author: David Maseda Neira
License-Expression: MIT
Classifier: Development Status :: 4 - Beta
Classifier: Intended Audience :: Developers
Classifier: License :: OSI Approved :: MIT License
Classifier: Operating System :: POSIX :: Linux
Classifier: Programming Language :: Python :: 3
Classifier: Programming Language :: Python :: 3.13
Classifier: Topic :: Multimedia :: Sound/Audio
Classifier: Topic :: Multimedia :: Video
Classifier: Topic :: Software Development :: Libraries :: Python Modules
Requires-Dist: mcp>=1.0.0
Requires-Dist: pygobject>=3.42.0
Requires-Dist: httpx>=0.27.0
Requires-Python: >=3.13
Project-URL: Homepage, https://github.com/wizenink/gst-mcp
Project-URL: Issues, https://github.com/wizenink/gst-mcp/issues
Project-URL: Repository, https://github.com/wizenink/gst-mcp
